1.py
MANIFEST.in
README.md
meta.py
setup.py
zip.zip
prime_math.egg-info/PKG-INFO
prime_math.egg-info/SOURCES.txt
prime_math.egg-info/dependency_links.txt
prime_math.egg-info/not-zip-safe
prime_math.egg-info/top_level.txt
resources/image1.png